myframe/__init__.py
myframe/_config.cp310-win_amd64.pyd
myframe/_container.cp310-win_amd64.pyd
myframe/config_casbin_model_rbac.conf
myframe/util.cp310-win_amd64.pyd
myframe/_script/__init__.py
myframe/_script/script_config.py
myframe/_script/script_token.py
myframe/service/__init__.cp310-win_amd64.pyd
myframe/service/__init__.py
myframe/service/_service_paramsign.cp310-win_amd64.pyd
myframe/service/service_casbin.cp310-win_amd64.pyd
myframe/service/service_cdn.cp310-win_amd64.pyd
myframe/service/service_httpclient.cp310-win_amd64.pyd
myframe/service/service_jwt.cp310-win_amd64.pyd
myframe/service/service_logger.cp310-win_amd64.pyd
myframe/service/service_mysql.cp310-win_amd64.pyd
myframe/service/service_redis.cp310-win_amd64.pyd
myframe-0.4.9.dist-info/METADATA
myframe-0.4.9.dist-info/WHEEL
myframe-0.4.9.dist-info/entry_points.txt
myframe-0.4.9.dist-info/top_level.txt
myframe-0.4.9.dist-info/RECORD
